CGIRMSLib/__init__.py
CGIRMSlib-0.1.dist-info/METADATA
CGIRMSlib-0.1.dist-info/WHEEL
CGIRMSlib-0.1.dist-info/top_level.txt
CGIRMSlib-0.1.dist-info/RECORD
