Metadata-Version: 2.1
Name: CGIRMSlib
Version: 0.1
Summary: Derivada para uso em conversões de python para o RMS
Author: CGI
Author-email: andre.ershov@cgi.com
Requires-Dist: pandas
Requires-Dist: datetime
